xkcd_get
