Metadata-Version: 1.1
Name: xkcd-get
Version: 0.0.2
Summary: downloader of xkcd comics
Home-page: https://github.com/tiagocoutinho/xkcd
Author: Tiago Coutinho
Author-email: coutinhotiago@gmail.com
License: UNKNOWN
Keywords: xkcd
Platform: UNKNOWN
Classifier: Programming Language :: Python :: 2.6
Classifier: Programming Language :: Python :: 2.7
Classifier: Programming Language :: Python :: 3.4
Classifier: Programming Language :: Python :: 3.5
Classifier: Programming Language :: Python :: 3.6
